titanic_model/VERSION
titanic_model/__init__.py
titanic_model/config.yml
titanic_model/pipeline.py
titanic_model/predict.py
titanic_model/train_pipeline.py
titanic_model/config/__init__.py
titanic_model/config/core.py
titanic_model/datasets/__init__.py
titanic_model/datasets/raw.csv
titanic_model/processing/__init__.py
titanic_model/processing/data_manager.py
titanic_model/processing/features.py
titanic_model/processing/validation.py
titanic_model/trained_models/__init__.py
titanic_model/trained_models/titanic_classification_model_output_v0.0.11.pkl
titanic_survival_model-0.0.11.dist-info/METADATA
titanic_survival_model-0.0.11.dist-info/WHEEL
titanic_survival_model-0.0.11.dist-info/top_level.txt
titanic_survival_model-0.0.11.dist-info/RECORD
